coras-0.0.3.dist-info/top_level.txt
coras-0.0.3.dist-info/WHEEL
coras-0.0.3.dist-info/METADATA
coras-0.0.3.dist-info/RECORD
coras-0.0.3.dist-info/DESCRIPTION.rst
coras-0.0.3.dist-info/metadata.json
CorasLib/APIException.py
CorasLib/Configuration.py
CorasLib/APIHelper.py
CorasLib/__init__.py
CorasLib/Models/AddressSerializer.py
CorasLib/Models/WriteAddressSerializer.py
CorasLib/Models/AllocationSnapshotSerializer.py
CorasLib/Models/PriceSerializer.py
CorasLib/Models/WriteAllocationSnapshotSerializer.py
CorasLib/Models/WriteSectionSerializer.py
CorasLib/Models/WritePriceSerializer.py
CorasLib/Models/AllocationRequestSerializer.py
CorasLib/Models/EventSerializer.py
CorasLib/Models/PriceChartSerializer.py
CorasLib/Models/WriteNotificationConfigSerializer.py
CorasLib/Models/VenueConfigurationSerializer.py
CorasLib/Models/AllocationSerializer.py
CorasLib/Models/WriteVenueConfigurationSerializer.py
CorasLib/Models/WriteAllocationRequestSerializer.py
CorasLib/Models/WriteDeviceSerializer.py
CorasLib/Models/WriteEventSerializer.py
CorasLib/Models/VenueSerializer.py
CorasLib/Models/WriteAllocationSerializer.py
CorasLib/Models/WriteVenueSerializer.py
CorasLib/Models/DeviceSerializer.py
CorasLib/Models/WritePriceChartSerializer.py
CorasLib/Models/CreatePriceChartParamPrices.py
CorasLib/Models/__init__.py
CorasLib/Models/NotificationConfigSerializer.py
CorasLib/Models/WriteAllocationItemSerializer.py
CorasLib/Models/SectionSerializer.py
CorasLib/Models/AllocationItemSerializer.py
CorasLib/Controllers/APIController.py
CorasLib/Controllers/__init__.py
