Metadata-Version: 2.0
Name: coras
Version: 0.0.3
Summary: Python Coras is a python SDK for the coras.io API.
Home-page: https://github.com/philroche/python_coras
Author: Philip Roche
Author-email: phil.roche@coras.io
License: ISCL
Keywords: coras
Platform: UNKNOWN
Classifier: Development Status :: 2 - Pre-Alpha
Classifier: Intended Audience :: Developers
Classifier: License :: OSI Approved :: ISC License (ISCL)
Classifier: Natural Language :: English
Classifier: Programming Language :: Python :: 2
Classifier: Programming Language :: Python :: 2.6
Classifier: Programming Language :: Python :: 2.7
Requires-Dist: Unirest (==1.1.6)
Requires-Dist: jsonpickle (==0.7.1)
Requires-Dist: poster (==0.8.1)
